fitpdf/__init__.py
fitpdf/general_helpers.py
fitpdf/plotting.py
fitpdf/stats.py
fitpdf/version.py
fitpdf/apps/__init__.py
fitpdf/apps/compare_fits.py
fitpdf/apps/fit_pdf.py
fitpdf/apps/simulate_dist.py
fitpdf/models/__init__.py
fitpdf/models/ll.py
fitpdf/models/model.py
fitpdf/models/nl.py
fitpdf/models/nn.py
fitpdf/models/nnl.py
fitpdf/models/nnp.py
fitpdf-0.4.2.dist-info/licenses/LICENSE
fitpdf-0.4.2.dist-info/METADATA
fitpdf-0.4.2.dist-info/WHEEL
fitpdf-0.4.2.dist-info/entry_points.txt
fitpdf-0.4.2.dist-info/top_level.txt
fitpdf-0.4.2.dist-info/RECORD
