Metadata-Version: 2.4
Name: fitpdf
Version: 0.4.2
Summary: Distribution fitting tools.
Author-email: Fabian Jankowski <fjankowsk@gmail.com>
Maintainer-email: Fabian Jankowski <fjankowsk@gmail.com>
License-Expression: MIT
Project-URL: Homepage, https://github.com/fjankowsk/fitpdf
Project-URL: Issues, https://github.com/fjankowsk/fitpdf/issues
Project-URL: Repository, https://github.com/fjankowsk/fitpdf.git
Keywords: distributions,fitting,fitting-distributions,data-analysis,astrophysics,pulsars,fast-radio-bursts,python
Classifier: Development Status :: 5 - Production/Stable
Classifier: Programming Language :: Python :: 3
Classifier: Operating System :: OS Independent
Requires-Python: >=3.9
License-File: LICENSE
Requires-Dist: arviz
Requires-Dist: corner
Requires-Dist: KDEpy
Requires-Dist: matplotlib
Requires-Dist: numpy
Requires-Dist: pandas
Requires-Dist: pymc
Requires-Dist: scipy
Requires-Dist: xarray
Provides-Extra: develop
Requires-Dist: black; extra == "develop"
Requires-Dist: build; extra == "develop"
Requires-Dist: twine; extra == "develop"
Dynamic: license-file
